pyeee/__init__.py
pyeee/_version.py
pyeee/eee.py
pyeee-4.1.12.dist-info/AUTHORS.rst
pyeee-4.1.12.dist-info/LICENSE
pyeee-4.1.12.dist-info/METADATA
pyeee-4.1.12.dist-info/WHEEL
pyeee-4.1.12.dist-info/top_level.txt
pyeee-4.1.12.dist-info/RECORD
